<annotation>
	<folder>train</folder>
	<filename>27_0.jpg</filename>
	<path>C:\tensorflow1\models\research\object_detection\images\train\27_0.jpg</path>
	<source>
		<database>Unknown</database>
	</source>
	<size>
		<width>288</width>
		<height>133</height>
		<depth>3</depth>
	</size>
	<segmented>0</segmented>
	<object>
		<name>4</name>
		<pose>Unspecified</pose>
		<truncated>0</truncated>
		<difficult>0</difficult>
		<bndbox>
			<xmin>142</xmin>
			<ymin>25</ymin>
			<xmax>172</xmax>
			<ymax>69</ymax>
		</bndbox>
	</object>
	<object>
		<name>1</name>
		<pose>Unspecified</pose>
		<truncated>0</truncated>
		<difficult>0</difficult>
		<bndbox>
			<xmin>174</xmin>
			<ymin>25</ymin>
			<xmax>200</xmax>
			<ymax>74</ymax>
		</bndbox>
	</object>
	<object>
		<name>4</name>
		<pose>Unspecified</pose>
		<truncated>0</truncated>
		<difficult>0</difficult>
		<bndbox>
			<xmin>203</xmin>
			<ymin>26</ymin>
			<xmax>229</xmax>
			<ymax>76</ymax>
		</bndbox>
	</object>
	<object>
		<name>8</name>
		<pose>Unspecified</pose>
		<truncated>0</truncated>
		<difficult>0</difficult>
		<bndbox>
			<xmin>231</xmin>
			<ymin>29</ymin>
			<xmax>258</xmax>
			<ymax>78</ymax>
		</bndbox>
	</object>
</annotation>
